{
	"settings": {
		"allocatedMemory": 4096,
		"gameResolution": {
			"width": "854",
			"height": "480",
			"fullscreen": false
		},
		"language": "en_US",
		"afterLaunchAction": "HIDE",
		"advancedMode": true,
		"gameDirectory": "C:\\Users\\pox\\AppData\\Roaming\\.minecraft",
		"gameBranch": "master",
		"discordRichPresence": {
			"enabled": true,
			"hideWhenIdle": false
		},
		"gameProfile": "lunar-1.21",
		"computerStartup": false,
		"exitToDock": false,
		"allowAnalyticsCollection": false,
		"missionControl": {
			"position": {
				"x": 0,
				"y": 0
			},
			"screen": 1350968926,
			"afterLaunchAction": "DONT_SHOW"
		},
		"launcherResolution": {
			"main": {
				"width": 1300,
				"height": 750
			},
			"mission-control": {
				"width": 1300,
				"height": 840
			}
		},
		"adsOptimization": false
	},
	"trackingIds": {
		"ga4": ""
	},
	"__internal__": {
		"migrations": {
			"version": "3.3.5-ow"
		}
	},
	"views": {
		"versions": {
			"displayType": "grid"
		},
		"servers": {
			"sort": "most-players"
		}
	},
	"launcherResolutions": {
		"main": {
			"width": 1920,
			"height": 1032
		},
		"chat": {
			"width": 565,
			"height": 500
		},
		"mission-control": {
			"width": 960,
			"height": 1032
		}
	},
	"updater": {
		"channel": "latest-ow",
		"streamUrl": "https://launcherupdates.lunarclientcdn.com"
	}
}